scrapy_djangoitem/__init__.py
scrapy_djangoitem-1.1.1.dist-info/DESCRIPTION.rst
scrapy_djangoitem-1.1.1.dist-info/METADATA
scrapy_djangoitem-1.1.1.dist-info/RECORD
scrapy_djangoitem-1.1.1.dist-info/WHEEL
scrapy_djangoitem-1.1.1.dist-info/metadata.json
scrapy_djangoitem-1.1.1.dist-info/top_level.txt
