Metadata-Version: 1.1
Name: scrapy-djangoitem
Version: 1.1.1
Summary: Scrapy extension to write scraped items using Django models
Home-page: https://github.com/scrapy-plugins/scrapy-djangoitem
Author: Scrapy developers
Author-email: UNKNOWN
License: BSD
Platform: UNKNOWN
Classifier: Framework :: Scrapy
Classifier: Development Status :: 5 - Production/Stable
Classifier: Environment :: Console
Classifier: Intended Audience :: Developers
Classifier: License :: OSI Approved :: BSD License
Classifier: Operating System :: OS Independent
Classifier: Programming Language :: Python
Classifier: Programming Language :: Python :: 2
Classifier: Programming Language :: Python :: 2.7
Classifier: Programming Language :: Python :: 3
Classifier: Programming Language :: Python :: 3.4
Classifier: Programming Language :: Python :: 3.5
Classifier: Topic :: Utilities
Classifier: Framework :: Django
Classifier: Framework :: Scrapy
Requires: scrapy (>=0.24.5)
Requires: django
